topsispackage_prabhnoorsingh/__init__.py
topsispackage_prabhnoorsingh/topsis.py
Topsis_Prabhnoor_102083037-1.0.0.dist-info/LICENSE
Topsis_Prabhnoor_102083037-1.0.0.dist-info/METADATA
Topsis_Prabhnoor_102083037-1.0.0.dist-info/WHEEL
Topsis_Prabhnoor_102083037-1.0.0.dist-info/top_level.txt
Topsis_Prabhnoor_102083037-1.0.0.dist-info/RECORD
