Metadata-Version: 2.1
Name: Topsis-Prabhnoor-102083037
Version: 1.0.0
Summary: A package to find the topsis score
Author: Prabhnoor Singh
Author-email: pchowdhary_be19@thapar.edu
License: UNKNOWN
Platform: UNKNOWN
Classifier: Programming Language :: Python :: 3
Classifier: License :: OSI Approved :: MIT License
Classifier: Operating System :: OS Independent
Requires-Python: >=3.6
License-File: LICENSE
Requires-Dist: requests
Requires-Dist: numpy
Requires-Dist: pandas
